gbcrawler/__init__.py
gbcrawler/gbcrawler.py
gbcrawler-0.3.0.dist-info/LICENSE
gbcrawler-0.3.0.dist-info/METADATA
gbcrawler-0.3.0.dist-info/WHEEL
gbcrawler-0.3.0.dist-info/top_level.txt
gbcrawler-0.3.0.dist-info/RECORD
