Metadata-Version: 2.1
Name: gbcrawler
Version: 0.3.0
Summary: Complete GenBank parser
Home-page: https://github.com/loalon/gbcrawler
Author: Alonso Serrano
Author-email: bioinformatics@loalon.com
License: UNKNOWN
Platform: UNKNOWN
Classifier: Programming Language :: Python :: 3
Classifier: License :: OSI Approved :: GNU General Public License v3 (GPLv3)
Classifier: Operating System :: OS Independent
Requires-Python: >=3.6
